MANIFEST.in
README.md
setup.py
anthill/static/__init__.py
anthill/static/admin.py
anthill/static/handler.py
anthill/static/options.py
anthill/static/server.py
anthill/static/model/__init__.py
anthill/static/model/deploy.py
anthill/static/model/settings.py
anthill/static/sql/settings.sql
anthill_static.egg-info/PKG-INFO
anthill_static.egg-info/SOURCES.txt
anthill_static.egg-info/dependency_links.txt
anthill_static.egg-info/namespace_packages.txt
anthill_static.egg-info/not-zip-safe
anthill_static.egg-info/requires.txt
anthill_static.egg-info/top_level.txt