Metadata-Version: 1.0
Name: anthill-static
Version: 0.2
Summary: Simple static files hosting service (for players to upload)
Home-page: https://github.com/anthill-platform/anthill-static
Author: desertkun
Author-email: desertkun@gmail.com
License: MIT
Platform: UNKNOWN
